pymctp/__about__.py
pymctp/__init__.py
pymctp/automaton/__init__.py
pymctp/automaton/manager.py
pymctp/automaton/sessions.py
pymctp/automaton/simple_endpoint.py
pymctp/cli/__init__.py
pymctp/cli/analyze_tcpdump.py
pymctp/cli/extensions.py
pymctp/cli/main.py
pymctp/cli/plugin_loader.py
pymctp/exerciser/__init__.py
pymctp/exerciser/plugin_loader.py
pymctp/layers/__init__.py
pymctp/layers/helpers.py
pymctp/layers/interfaces.py
pymctp/layers/plugin_loader.py
pymctp/layers/ipmi/__init__.py
pymctp/layers/ipmi/transport.py
pymctp/layers/mctp/__init__.py
pymctp/layers/mctp/context_utils.py
pymctp/layers/mctp/transport.py
pymctp/layers/mctp/types.py
pymctp/layers/mctp/control/__init__.py
pymctp/layers/mctp/control/allocate_eids.py
pymctp/layers/mctp/control/control.py
pymctp/layers/mctp/control/discovery_notify.py
pymctp/layers/mctp/control/get_eid.py
pymctp/layers/mctp/control/get_eid_uuid.py
pymctp/layers/mctp/control/get_mctp_version_support.py
pymctp/layers/mctp/control/get_msg_type_support.py
pymctp/layers/mctp/control/get_routing_table_entries.py
pymctp/layers/mctp/control/get_vdm_support.py
pymctp/layers/mctp/control/prepare_for_endpoint_discovery.py
pymctp/layers/mctp/control/routing_info_update.py
pymctp/layers/mctp/control/set_eid.py
pymctp/layers/mctp/control/types.py
pymctp/layers/mctp/nvmemi/__init__.py
pymctp/layers/mctp/nvmemi/nvmemi.py
pymctp/layers/mctp/nvmemi/types.py
pymctp/layers/mctp/pldm/__init__.py
pymctp/layers/mctp/pldm/pldm.py
pymctp/layers/mctp/pldm/type1_base.py
pymctp/layers/mctp/pldm/type_2_platform_monitoring.py
pymctp/layers/mctp/pldm/types.py
pymctp/layers/mctp/vdpci/__init__.py
pymctp/layers/mctp/vdpci/types.py
pymctp/layers/mctp/vdpci/vdpci.py
pymctp/oem/__init__.py
pymctp/utils/__init__.py
pymctp/utils/helpers.py
pymctp-0.2.8.dist-info/METADATA
pymctp-0.2.8.dist-info/WHEEL
pymctp-0.2.8.dist-info/entry_points.txt
pymctp-0.2.8.dist-info/licenses/LICENSE
pymctp-0.2.8.dist-info/RECORD
