Metadata-Version: 2.4
Name: pymctp
Version: 0.2.8
Summary: PyMCTP is a tool to craft/decode DMTF MCTP communication packets
Project-URL: Documentation, https://github.com/jls5177/pymctp#readme
Project-URL: Issues, https://github.com/jls5177/pymctp/issues
Project-URL: Source, https://github.com/jls5177/pymctp
Author-email: Justin Simon <justin@simonctl.com>
License: MIT License
License-File: LICENSE
Classifier: Development Status :: 4 - Beta
Classifier: Intended Audience :: Developers
Classifier: Programming Language :: Python
Classifier: Programming Language :: Python :: 3.8
Classifier: Programming Language :: Python :: 3.9
Classifier: Programming Language :: Python :: 3.10
Classifier: Programming Language :: Python :: 3.11
Classifier: Programming Language :: Python :: 3.12
Classifier: Programming Language :: Python :: Implementation :: CPython
Classifier: Programming Language :: Python :: Implementation :: PyPy
Classifier: Topic :: Software Development :: Libraries
Classifier: Topic :: Utilities
Requires-Python: >=3.8
Requires-Dist: click>=8.0
Requires-Dist: crc8>=0.1.0
Requires-Dist: crcmod-plus
Requires-Dist: mashumaro>=3.5
Requires-Dist: pytz
Requires-Dist: scapy>=2.5.0
Requires-Dist: tzlocal
Provides-Extra: aardvark
Requires-Dist: pymctp-exerciser-aardvark>=0.2.0; extra == 'aardvark'
Provides-Extra: all-exercisers
Requires-Dist: pymctp-exerciser-aardvark>=0.2.0; extra == 'all-exercisers'
Requires-Dist: pymctp-exerciser-qemu>=0.2.0; extra == 'all-exercisers'
Requires-Dist: pymctp-exerciser-serial>=0.2.0; extra == 'all-exercisers'
Provides-Extra: qemu
Requires-Dist: pymctp-exerciser-qemu>=0.2.0; extra == 'qemu'
Provides-Extra: serial
Requires-Dist: pymctp-exerciser-serial>=0.2.0; extra == 'serial'
